Metadata-Version: 2.1
Name: dcoder
Version: 0.2.0
Summary: A module that can decode/encode text in various ciphers.
Home-page: https://github.com/CodeWithSwastik/dcoder
Author: Swas.py
Author-email: cwswas.py@gmail.com
License: MIT
Keywords: decoder,encoder,ciphers
Platform: UNKNOWN
Classifier: Development Status :: 5 - Production/Stable
Classifier: Intended Audience :: Developers
Classifier: License :: OSI Approved :: MIT License
Classifier: Programming Language :: Python :: 3
